git_archive_all.py
git_archive_all-1.23.1.dist-info/LICENSE.txt
git_archive_all-1.23.1.dist-info/METADATA
git_archive_all-1.23.1.dist-info/WHEEL
git_archive_all-1.23.1.dist-info/entry_points.txt
git_archive_all-1.23.1.dist-info/top_level.txt
git_archive_all-1.23.1.dist-info/zip-safe
git_archive_all-1.23.1.dist-info/RECORD
