Metadata-Version: 2.1
Name: git-archive-all
Version: 1.23.1
Summary: Archive git repository with its submodules.
Home-page: https://github.com/Kentzo/git-archive-all
Author: Ilya Kulakov
Author-email: kulakov.ilya@gmail.com
License: MIT License
Platform: Darwin
Platform: Linux
Platform: Windows
Classifier: Development Status :: 5 - Production/Stable
Classifier: Environment :: Console
Classifier: Intended Audience :: Developers
Classifier: Intended Audience :: System Administrators
Classifier: License :: OSI Approved :: MIT License
Classifier: Natural Language :: English
Classifier: Programming Language :: Python :: Implementation :: CPython
Classifier: Programming Language :: Python :: Implementation :: PyPy
Classifier: Programming Language :: Python :: 2
Classifier: Programming Language :: Python :: 2.6
Classifier: Programming Language :: Python :: 2.7
Classifier: Programming Language :: Python :: 3
Classifier: Programming Language :: Python :: 3.4
Classifier: Programming Language :: Python :: 3.5
Classifier: Programming Language :: Python :: 3.6
Classifier: Programming Language :: Python :: 3.7
Classifier: Programming Language :: Python :: 3.8
Classifier: Programming Language :: Python :: 3.9
Classifier: Topic :: Software Development :: Version Control
Classifier: Topic :: System :: Archiving
Requires-Python: !=3.0.*,!=3.1.*,!=3.2.*,!=3.3.*,>=2.6
License-File: LICENSE.txt
